pyhtml/__init__.py
pyhtml/__render_options.py
pyhtml/__tag_base.py
pyhtml/__tags/__init__.py
pyhtml/__tags/comment.py
pyhtml/__tags/dangerous_raw_html.py
pyhtml/__tags/element_group.py
pyhtml/__tags/generated.py
pyhtml/__tags/input_tag.py
pyhtml/__tags/renames.py
pyhtml/__types.py
pyhtml/__util.py
pyhtml/py.typed
pyhtml_enhanced-2.3.0.dist-info/WHEEL
pyhtml_enhanced-2.3.0.dist-info/METADATA
pyhtml_enhanced-2.3.0.dist-info/RECORD
