Metadata-Version: 2.3
Name: pyhtml-enhanced
Version: 2.3.0
Summary: A library for building HTML documents with a simple and learnable syntax
Keywords: html,template,pyhtml,markup,documentation
Author: Maddy Guthridge
Author-email: Maddy Guthridge <maddy.guthridge@unsw.edu.au>
License: MIT
Classifier: Programming Language :: Python :: 3
Classifier: Intended Audience :: Developers
Classifier: Intended Audience :: Education
Classifier: License :: OSI Approved :: MIT License
Classifier: Operating System :: OS Independent
Classifier: Development Status :: 5 - Production/Stable
Classifier: Topic :: Internet :: WWW/HTTP :: Dynamic Content
Classifier: Topic :: Internet :: WWW/HTTP :: Dynamic Content :: CGI Tools/Libraries
Classifier: Typing :: Typed
Requires-Dist: typing-extensions>=4.12.2
Requires-Python: >=3.10
Project-URL: homepage, https://comp1010unsw.github.io/pyhtml-enhanced/
Project-URL: repository, https://github.com/COMP1010UNSW/pyhtml-enhanced
Project-URL: documentation, https://comp1010unsw.github.io/pyhtml-enhanced/
Project-URL: Bug Tracker, https://github.com/COMP1010UNSW/pyhtml-enhanced/issues
